{
  "_class": "shapeGroup",
  "booleanOperation": 0,
  "clippingMaskMode": 0,
  "do_objectID": "9A45FC88-378E-430B-B2A7-C897D7556163",
  "exportOptions": {
    "_class": "exportOptions",
    "do_objectID": "344BC866-0733-4D9D-8D9A-A8BE9BDE3042",
    "exportFormats": [
    ],
    "includedLayerIds": [
    ],
    "layerOptions": 0,
    "shouldTrim": false
  },
  "frame": {
    "_class": "rect",
    "constrainProportions": false,
    "do_objectID": "BC11172E-2166-4E7B-823B-12201A9F7BE7",
    "height": 18,
    "width": 18,
    "x": 3,
    "y": 3
  },
  "groupLayout": {
    "_class": "MSImmutableFreeformGroupLayout",
    "do_objectID": "0711F5F8-040A-4ED4-B12E-DB6D408E16D8"
  },
  "hasClickThrough": false,
  "hasClippingMask": true,
  "isFixedToViewport": false,
  "isFlippedHorizontal": false,
  "isFlippedVertical": false,
  "isLocked": false,
  "isVisible": true,
  "layerListExpandedType": 1,
  "layers": [
    {
      "class": "shapePath",
      "id": "0BB3A770-5D26-4CA6-A4F3-EAF21BA38957"
    },
    {
      "class": "shapePath",
      "id": "DB40E691-5EA9-47AD-B276-05A75EC555AC"
    }
  ],
  "name": "icon/action/exit_to_app_24px",
  "nameIsFixed": false,
  "resizingConstraint": 63,
  "resizingType": 0,
  "rotation": 0,
  "shouldBreakMaskChain": false,
  "style": {
    "_class": "style",
    "do_objectID": "C4F030C0-197E-40E5-9FDA-F385DCC53D91",
    "endMarkerType": 0,
    "fills": [
      {
        "_class": "fill",
        "color": {
          "_class": "color",
          "alpha": 1,
          "blue": 0,
          "green": 0,
          "red": 0
        },
        "fillType": 0,
        "isEnabled": false,
        "noiseIndex": 0,
        "noiseIntensity": 0,
        "patternFillType": 1,
        "patternTileScale": 1
      }
    ],
    "miterLimit": 10,
    "startMarkerType": 0,
    "windingRule": 0
  },
  "windingRule": 0
}