{
  "_class": "shapePath",
  "booleanOperation": -1,
  "clippingMaskMode": 0,
  "do_objectID": "1D1EA93B-E245-4619-AFEB-33C6026250B1",
  "edited": true,
  "exportOptions": {
    "_class": "exportOptions",
    "do_objectID": "78F650DE-4BE4-4B54-AA5A-F07CCCE51B1A",
    "exportFormats": [
    ],
    "includedLayerIds": [
    ],
    "layerOptions": 0,
    "shouldTrim": false
  },
  "frame": {
    "_class": "rect",
    "constrainProportions": false,
    "do_objectID": "5882357E-30E5-425E-9BF2-26D074233EE9",
    "height": 6,
    "width": 8,
    "x": 0,
    "y": 18
  },
  "hasClippingMask": false,
  "isClosed": true,
  "isFixedToViewport": false,
  "isFlippedHorizontal": false,
  "isFlippedVertical": false,
  "isLocked": false,
  "isVisible": true,
  "layerListExpandedType": 0,
  "name": "Path",
  "nameIsFixed": false,
  "pointRadiusBehaviour": 1,
  "points": [
    {
      "_class": "curvePoint",
      "cornerRadius": 0,
      "curveFrom": "{0.625, 0.33333333333333331}",
      "curveMode": 1,
      "curveTo": "{0.625, 0.33333333333333331}",
      "hasCurveFrom": false,
      "hasCurveTo": false,
      "point": "{0.625, 0.33333333333333331}"
    },
    {
      "_class": "curvePoint",
      "cornerRadius": 0,
      "curveFrom": "{0, 0.33333333333333331}",
      "curveMode": 1,
      "curveTo": "{0, 0.33333333333333331}",
      "hasCurveFrom": false,
      "hasCurveTo": false,
      "point": "{0, 0.33333333333333331}"
    },
    {
      "_class": "curvePoint",
      "cornerRadius": 0,
      "curveFrom": "{0, 0.66666666666666663}",
      "curveMode": 1,
      "curveTo": "{0, 0.66666666666666663}",
      "hasCurveFrom": false,
      "hasCurveTo": false,
      "point": "{0, 0.66666666666666663}"
    },
    {
      "_class": "curvePoint",
      "cornerRadius": 0,
      "curveFrom": "{0.625, 0.66666666666666663}",
      "curveMode": 1,
      "curveTo": "{0.625, 0.66666666666666663}",
      "hasCurveFrom": false,
      "hasCurveTo": false,
      "point": "{0.625, 0.66666666666666663}"
    },
    {
      "_class": "curvePoint",
      "cornerRadius": 0,
      "curveFrom": "{0.625, 1}",
      "curveMode": 1,
      "curveTo": "{0.625, 1}",
      "hasCurveFrom": false,
      "hasCurveTo": false,
      "point": "{0.625, 1}"
    },
    {
      "_class": "curvePoint",
      "cornerRadius": 0,
      "curveFrom": "{1, 0.5}",
      "curveMode": 1,
      "curveTo": "{1, 0.5}",
      "hasCurveFrom": false,
      "hasCurveTo": false,
      "point": "{1, 0.5}"
    },
    {
      "_class": "curvePoint",
      "cornerRadius": 0,
      "curveFrom": "{0.625, 0}",
      "curveMode": 1,
      "curveTo": "{0.625, 0}",
      "hasCurveFrom": false,
      "hasCurveTo": false,
      "point": "{0.625, 0}"
    }
  ],
  "resizingConstraint": 63,
  "resizingType": 0,
  "rotation": 0,
  "shouldBreakMaskChain": false,
  "style": {
    "_class": "style",
    "do_objectID": "1794E3A0-5341-43A2-8F3E-EA3D123CA12D",
    "endMarkerType": 0,
    "fills": [
      {
        "_class": "fill",
        "color": {
          "_class": "color",
          "alpha": 1,
          "blue": 0,
          "green": 0,
          "red": 0
        },
        "fillType": 0,
        "isEnabled": false,
        "noiseIndex": 0,
        "noiseIntensity": 0,
        "patternFillType": 1,
        "patternTileScale": 1
      }
    ],
    "miterLimit": 10,
    "startMarkerType": 0,
    "windingRule": 0
  }
}