{
  "_class": "symbolMaster",
  "backgroundColor": {
    "_class": "color",
    "alpha": 1,
    "blue": 1,
    "do_objectID": "51D4DE54-510C-48F3-97B2-BCF2CE3C8AC9",
    "green": 1,
    "red": 1
  },
  "booleanOperation": 0,
  "changeIdentifier": 487,
  "clippingMaskMode": 0,
  "do_objectID": "60A91D02-9716-469B-8E75-53685D42E9DC",
  "exportOptions": {
    "_class": "exportOptions",
    "do_objectID": "85171FC8-B7DC-4A87-8C9A-D6BE75E66BCC",
    "exportFormats": [
    ],
    "includedLayerIds": [
    ],
    "layerOptions": 0,
    "shouldTrim": false
  },
  "frame": {
    "_class": "rect",
    "constrainProportions": false,
    "do_objectID": "3288C393-F2BD-4EBA-95A1-DEDFC8C21A51",
    "height": 24,
    "width": 24,
    "x": 1275,
    "y": 421
  },
  "groupLayout": {
    "_class": "MSImmutableFreeformGroupLayout",
    "do_objectID": "EFCBDEE8-FCA9-4709-9419-DCDBEE932FCC"
  },
  "hasBackgroundColor": false,
  "hasClickThrough": true,
  "hasClippingMask": false,
  "horizontalRulerData": {
    "_class": "rulerData",
    "base": 0,
    "do_objectID": "B7986B0A-3E42-4F88-8B0A-70C3836D9494",
    "guides": [
    ]
  },
  "includeBackgroundColorInExport": true,
  "includeBackgroundColorInInstance": true,
  "includeInCloudUpload": true,
  "isFixedToViewport": false,
  "isFlippedHorizontal": false,
  "isFlippedVertical": false,
  "isFlowHome": false,
  "isLocked": false,
  "isVisible": true,
  "layerListExpandedType": 0,
  "layers": [
    {
      "class": "shapeGroup",
      "id": "CDB11502-9924-4130-92B9-7035C2A6B21D"
    },
    {
      "class": "symbolInstance",
      "id": "5CD37864-DEA5-48F1-AD0F-935E533C4D0A"
    }
  ],
  "name": "icon/image/photo_24px",
  "nameIsFixed": false,
  "overrideProperties": [
    {
      "_class": "MSImmutableOverrideProperty",
      "canOverride": true,
      "overrideName": "5CD37864-DEA5-48F1-AD0F-935E533C4D0A_symbolID"
    }
  ],
  "resizesContent": false,
  "resizingConstraint": 63,
  "resizingType": 0,
  "rotation": 0,
  "shouldBreakMaskChain": true,
  "style": {
    "_class": "style",
    "do_objectID": "78A52A41-38D3-420D-AC6B-B6E7C60AD33E",
    "endMarkerType": 0,
    "miterLimit": 10,
    "startMarkerType": 0,
    "windingRule": 1
  },
  "symbolID": "E6D44B93-49A0-42D6-B2E7-C5E72E933FA4",
  "userInfo": {
    "com.amoreaux.sketch-icons": {
      "color": "E5F72CF9-765C-453C-BB5F-4971859D9CB9",
      "padding": 0
    },
    "com.google.ux.material.spec_tools": {
      "iconStyle": "FILLED",
      "symbolName": "icon/image/photo_24px",
      "type": "icon"
    }
  },
  "verticalRulerData": {
    "_class": "rulerData",
    "base": 0,
    "do_objectID": "D82125CF-065E-4E45-BB17-8C8367BD9F15",
    "guides": [
    ]
  }
}