{
  "_class": "symbolInstance",
  "booleanOperation": 0,
  "clippingMaskMode": 0,
  "do_objectID": "53A34FE1-B9D6-43F9-99A5-82631153BE6B",
  "exportOptions": {
    "_class": "exportOptions",
    "do_objectID": "D18CE238-A6E0-4AA1-BEDC-B730244BA4AF",
    "exportFormats": [
    ],
    "includedLayerIds": [
    ],
    "layerOptions": 0,
    "shouldTrim": false
  },
  "frame": {
    "_class": "rect",
    "constrainProportions": false,
    "do_objectID": "E0EBE9F4-47DA-4393-A7E0-F41761942155",
    "height": 24,
    "width": 24,
    "x": 0,
    "y": 0
  },
  "hasClippingMask": false,
  "horizontalSpacing": 0,
  "isFixedToViewport": false,
  "isFlippedHorizontal": false,
  "isFlippedVertical": false,
  "isLocked": false,
  "isVisible": true,
  "layerListExpandedType": 0,
  "name": "↳ Color",
  "nameIsFixed": false,
  "overrideValues": [
  ],
  "resizingConstraint": 63,
  "resizingType": 0,
  "rotation": 0,
  "scale": 1,
  "shouldBreakMaskChain": false,
  "style": {
    "_class": "style",
    "do_objectID": "EBE92DEE-506B-47C9-91B1-859D83F7BEDE",
    "endMarkerType": 0,
    "miterLimit": 10,
    "startMarkerType": 0,
    "windingRule": 1
  },
  "symbolID": "644C9856-4728-41E1-A524-9F2EFF68D7F2",
  "verticalSpacing": 0
}