{
  "_class": "shapePath",
  "booleanOperation": -1,
  "clippingMaskMode": 0,
  "do_objectID": "BD089F9B-35FF-4DE0-9D80-46C6B756EBFB",
  "edited": true,
  "exportOptions": {
    "_class": "exportOptions",
    "do_objectID": "76BCAD6A-78DE-4024-A6F6-F399B4B366B7",
    "exportFormats": [
    ],
    "includedLayerIds": [
    ],
    "layerOptions": 0,
    "shouldTrim": false
  },
  "frame": {
    "_class": "rect",
    "constrainProportions": false,
    "do_objectID": "5E5CFE84-15A3-48B3-ADD1-5CF589CCB74C",
    "height": 16,
    "width": 16,
    "x": 4,
    "y": 0
  },
  "hasClippingMask": false,
  "isClosed": true,
  "isFixedToViewport": false,
  "isFlippedHorizontal": false,
  "isFlippedVertical": false,
  "isLocked": false,
  "isVisible": true,
  "layerListExpandedType": 0,
  "name": "Path",
  "nameIsFixed": false,
  "pointRadiusBehaviour": 1,
  "points": [
    {
      "_class": "curvePoint",
      "cornerRadius": 0,
      "curveFrom": "{1, 0.875}",
      "curveMode": 4,
      "curveTo": "{1, 0.94375000000000009}",
      "hasCurveFrom": false,
      "hasCurveTo": true,
      "point": "{1, 0.875}"
    },
    {
      "_class": "curvePoint",
      "cornerRadius": 0,
      "curveFrom": "{1, 0.056249999999999994}",
      "curveMode": 4,
      "curveTo": "{1, 0.125}",
      "hasCurveFrom": true,
      "hasCurveTo": false,
      "point": "{1, 0.125}"
    },
    {
      "_class": "curvePoint",
      "cornerRadius": 0,
      "curveFrom": "{0.875, 0}",
      "curveMode": 4,
      "curveTo": "{0.94375000000000009, 0}",
      "hasCurveFrom": false,
      "hasCurveTo": true,
      "point": "{0.875, 0}"
    },
    {
      "_class": "curvePoint",
      "cornerRadius": 0,
      "curveFrom": "{0.056250000000000022, 0}",
      "curveMode": 4,
      "curveTo": "{0.125, 0}",
      "hasCurveFrom": true,
      "hasCurveTo": false,
      "point": "{0.125, 0}"
    },
    {
      "_class": "curvePoint",
      "cornerRadius": 0,
      "curveFrom": "{0, 0.125}",
      "curveMode": 4,
      "curveTo": "{0, 0.056249999999999994}",
      "hasCurveFrom": false,
      "hasCurveTo": true,
      "point": "{0, 0.125}"
    },
    {
      "_class": "curvePoint",
      "cornerRadius": 0,
      "curveFrom": "{0, 0.94375000000000009}",
      "curveMode": 4,
      "curveTo": "{0, 0.875}",
      "hasCurveFrom": true,
      "hasCurveTo": false,
      "point": "{0, 0.875}"
    },
    {
      "_class": "curvePoint",
      "cornerRadius": 0,
      "curveFrom": "{0.125, 1}",
      "curveMode": 4,
      "curveTo": "{0.056250000000000022, 1}",
      "hasCurveFrom": false,
      "hasCurveTo": true,
      "point": "{0.125, 1}"
    },
    {
      "_class": "curvePoint",
      "cornerRadius": 0,
      "curveFrom": "{0.94375000000000009, 1}",
      "curveMode": 4,
      "curveTo": "{0.875, 1}",
      "hasCurveFrom": true,
      "hasCurveTo": false,
      "point": "{0.875, 1}"
    }
  ],
  "resizingConstraint": 63,
  "resizingType": 0,
  "rotation": 0,
  "shouldBreakMaskChain": false,
  "style": {
    "_class": "style",
    "do_objectID": "71A7605B-8FC4-4E73-9DCC-D642CADF65C1",
    "endMarkerType": 0,
    "fills": [
      {
        "_class": "fill",
        "color": {
          "_class": "color",
          "alpha": 1,
          "blue": 0,
          "green": 0,
          "red": 0
        },
        "fillType": 0,
        "isEnabled": false,
        "noiseIndex": 0,
        "noiseIntensity": 0,
        "patternFillType": 1,
        "patternTileScale": 1
      }
    ],
    "miterLimit": 10,
    "startMarkerType": 0,
    "windingRule": 0
  }
}