{
  "_class": "shapePath",
  "booleanOperation": -1,
  "clippingMaskMode": 0,
  "do_objectID": "0B5D6EA9-618C-4035-90C7-C77A0AA5D72F",
  "edited": true,
  "exportOptions": {
    "_class": "exportOptions",
    "do_objectID": "1E61E6AE-CD89-48AB-B688-C9B7ADD218FB",
    "exportFormats": [
    ],
    "includedLayerIds": [
    ],
    "layerOptions": 0,
    "shouldTrim": false
  },
  "frame": {
    "_class": "rect",
    "constrainProportions": false,
    "do_objectID": "CFBB37FE-05B1-4359-A55D-5EEB11C13536",
    "height": 16,
    "width": 23,
    "x": 0.5,
    "y": 4
  },
  "hasClippingMask": true,
  "isClosed": true,
  "isFixedToViewport": false,
  "isFlippedHorizontal": false,
  "isFlippedVertical": false,
  "isLocked": false,
  "isVisible": true,
  "layerListExpandedType": 1,
  "name": "icon/action/polymer_24px",
  "nameIsFixed": false,
  "pointRadiusBehaviour": 1,
  "points": [
    {
      "_class": "curvePoint",
      "cornerRadius": 0,
      "curveFrom": "{0.80434782608695654, 0}",
      "curveMode": 1,
      "curveTo": "{0.80434782608695654, 0}",
      "hasCurveFrom": false,
      "hasCurveTo": false,
      "point": "{0.80434782608695654, 0}"
    },
    {
      "_class": "curvePoint",
      "cornerRadius": 0,
      "curveFrom": "{0.63043478260869568, 0}",
      "curveMode": 1,
      "curveTo": "{0.63043478260869568, 0}",
      "hasCurveFrom": false,
      "hasCurveTo": false,
      "point": "{0.63043478260869568, 0}"
    },
    {
      "_class": "curvePoint",
      "cornerRadius": 0,
      "curveFrom": "{0.28739130434782612, 0.78937499999999994}",
      "curveMode": 1,
      "curveTo": "{0.28739130434782612, 0.78937499999999994}",
      "hasCurveFrom": false,
      "hasCurveTo": false,
      "point": "{0.28739130434782612, 0.78937499999999994}"
    },
    {
      "_class": "curvePoint",
      "cornerRadius": 0,
      "curveFrom": "{0.17391304347826086, 0.5}",
      "curveMode": 1,
      "curveTo": "{0.17391304347826086, 0.5}",
      "hasCurveFrom": false,
      "hasCurveTo": false,
      "point": "{0.17391304347826086, 0.5}"
    },
    {
      "_class": "curvePoint",
      "cornerRadius": 0,
      "curveFrom": "{0.36956521739130432, 0}",
      "curveMode": 1,
      "curveTo": "{0.36956521739130432, 0}",
      "hasCurveFrom": false,
      "hasCurveTo": false,
      "point": "{0.36956521739130432, 0}"
    },
    {
      "_class": "curvePoint",
      "cornerRadius": 0,
      "curveFrom": "{0.19565217391304349, 0}",
      "curveMode": 1,
      "curveTo": "{0.19565217391304349, 0}",
      "hasCurveFrom": false,
      "hasCurveTo": false,
      "point": "{0.19565217391304349, 0}"
    },
    {
      "_class": "curvePoint",
      "cornerRadius": 0,
      "curveFrom": "{0, 0.5}",
      "curveMode": 1,
      "curveTo": "{0, 0.5}",
      "hasCurveFrom": false,
      "hasCurveTo": false,
      "point": "{0, 0.5}"
    },
    {
      "_class": "curvePoint",
      "cornerRadius": 0,
      "curveFrom": "{0.19565217391304349, 1}",
      "curveMode": 1,
      "curveTo": "{0.19565217391304349, 1}",
      "hasCurveFrom": false,
      "hasCurveTo": false,
      "point": "{0.19565217391304349, 1}"
    },
    {
      "_class": "curvePoint",
      "cornerRadius": 0,
      "curveFrom": "{0.36956521739130432, 1}",
      "curveMode": 1,
      "curveTo": "{0.36956521739130432, 1}",
      "hasCurveFrom": false,
      "hasCurveTo": false,
      "point": "{0.36956521739130432, 1}"
    },
    {
      "_class": "curvePoint",
      "cornerRadius": 0,
      "curveFrom": "{0.71260869565217388, 0.21062499999999995}",
      "curveMode": 1,
      "curveTo": "{0.71260869565217388, 0.21062499999999995}",
      "hasCurveFrom": false,
      "hasCurveTo": false,
      "point": "{0.71260869565217388, 0.21062499999999995}"
    },
    {
      "_class": "curvePoint",
      "cornerRadius": 0,
      "curveFrom": "{0.82608695652173914, 0.5}",
      "curveMode": 1,
      "curveTo": "{0.82608695652173914, 0.5}",
      "hasCurveFrom": false,
      "hasCurveTo": false,
      "point": "{0.82608695652173914, 0.5}"
    },
    {
      "_class": "curvePoint",
      "cornerRadius": 0,
      "curveFrom": "{0.63043478260869568, 1}",
      "curveMode": 1,
      "curveTo": "{0.63043478260869568, 1}",
      "hasCurveFrom": false,
      "hasCurveTo": false,
      "point": "{0.63043478260869568, 1}"
    },
    {
      "_class": "curvePoint",
      "cornerRadius": 0,
      "curveFrom": "{0.80434782608695654, 1}",
      "curveMode": 1,
      "curveTo": "{0.80434782608695654, 1}",
      "hasCurveFrom": false,
      "hasCurveTo": false,
      "point": "{0.80434782608695654, 1}"
    },
    {
      "_class": "curvePoint",
      "cornerRadius": 0,
      "curveFrom": "{1, 0.5}",
      "curveMode": 1,
      "curveTo": "{1, 0.5}",
      "hasCurveFrom": false,
      "hasCurveTo": false,
      "point": "{1, 0.5}"
    }
  ],
  "resizingConstraint": 63,
  "resizingType": 0,
  "rotation": 0,
  "shouldBreakMaskChain": false,
  "style": {
    "_class": "style",
    "do_objectID": "A2DCAFD0-E7CE-417F-A424-D857C85D988A",
    "endMarkerType": 0,
    "fills": [
      {
        "_class": "fill",
        "color": {
          "_class": "color",
          "alpha": 1,
          "blue": 0,
          "green": 0,
          "red": 0
        },
        "fillType": 0,
        "isEnabled": false,
        "noiseIndex": 0,
        "noiseIntensity": 0,
        "patternFillType": 1,
        "patternTileScale": 1
      }
    ],
    "miterLimit": 10,
    "startMarkerType": 0,
    "windingRule": 0
  }
}