{
  "_class": "shapePath",
  "booleanOperation": -1,
  "clippingMaskMode": 0,
  "do_objectID": "57233C9A-08A5-40C4-AF02-4E8E7BCB657E",
  "edited": true,
  "exportOptions": {
    "_class": "exportOptions",
    "do_objectID": "6005CA49-365A-42E4-AD14-6689A6C322E8",
    "exportFormats": [
    ],
    "includedLayerIds": [
    ],
    "layerOptions": 0,
    "shouldTrim": false
  },
  "frame": {
    "_class": "rect",
    "constrainProportions": false,
    "do_objectID": "F2E3BF5E-933F-4CCC-AA0D-C96851E1220C",
    "height": 1.990000000000002,
    "width": 15.01,
    "x": 0,
    "y": 20
  },
  "hasClippingMask": false,
  "isClosed": true,
  "isFixedToViewport": false,
  "isFlippedHorizontal": false,
  "isFlippedVertical": false,
  "isLocked": false,
  "isVisible": true,
  "layerListExpandedType": 0,
  "name": "Path",
  "nameIsFixed": false,
  "pointRadiusBehaviour": 1,
  "points": [
    {
      "_class": "curvePoint",
      "cornerRadius": 0,
      "curveFrom": "{0, 0.77386934673366714}",
      "curveMode": 4,
      "curveTo": "{0, 0.49246231155778869}",
      "hasCurveFrom": true,
      "hasCurveTo": false,
      "point": "{0, 0.49246231155778869}"
    },
    {
      "_class": "curvePoint",
      "cornerRadius": 0,
      "curveFrom": "{0.067288474350433017, 1}",
      "curveMode": 4,
      "curveTo": "{0.029980013324450359, 1}",
      "hasCurveFrom": false,
      "hasCurveTo": true,
      "point": "{0.067288474350433017, 1}"
    },
    {
      "_class": "curvePoint",
      "cornerRadius": 0,
      "curveFrom": "{0.97001998667554956, 1}",
      "curveMode": 4,
      "curveTo": "{0.93271152564956683, 1}",
      "hasCurveFrom": true,
      "hasCurveTo": false,
      "point": "{0.93271152564956683, 1}"
    },
    {
      "_class": "curvePoint",
      "cornerRadius": 0,
      "curveFrom": "{1, 0.49246231155778869}",
      "curveMode": 4,
      "curveTo": "{1, 0.77386934673366892}",
      "hasCurveFrom": false,
      "hasCurveTo": true,
      "point": "{1, 0.49246231155778869}"
    },
    {
      "_class": "curvePoint",
      "cornerRadius": 0,
      "curveFrom": "{1, 0}",
      "curveMode": 1,
      "curveTo": "{1, 0}",
      "hasCurveFrom": false,
      "hasCurveTo": false,
      "point": "{1, 0}"
    },
    {
      "_class": "curvePoint",
      "cornerRadius": 0,
      "curveFrom": "{0, 0}",
      "curveMode": 1,
      "curveTo": "{0, 0}",
      "hasCurveFrom": false,
      "hasCurveTo": false,
      "point": "{0, 0}"
    }
  ],
  "resizingConstraint": 63,
  "resizingType": 0,
  "rotation": 0,
  "shouldBreakMaskChain": false,
  "style": {
    "_class": "style",
    "do_objectID": "C9299B46-4508-4BF4-B46B-A73C33BA58F1",
    "endMarkerType": 0,
    "fills": [
      {
        "_class": "fill",
        "color": {
          "_class": "color",
          "alpha": 1,
          "blue": 0,
          "green": 0,
          "red": 0
        },
        "fillType": 0,
        "isEnabled": false,
        "noiseIndex": 0,
        "noiseIntensity": 0,
        "patternFillType": 1,
        "patternTileScale": 1
      }
    ],
    "miterLimit": 10,
    "startMarkerType": 0,
    "windingRule": 0
  }
}