{
  "_class": "symbolMaster",
  "backgroundColor": {
    "_class": "color",
    "alpha": 1,
    "blue": 1,
    "do_objectID": "7D5FD516-4D6F-4CAB-855F-5F7D916348C8",
    "green": 1,
    "red": 1
  },
  "booleanOperation": 0,
  "changeIdentifier": 441,
  "clippingMaskMode": 0,
  "do_objectID": "9D9EE5C8-1D6A-4104-B2C9-EC86ADA4CAC0",
  "exportOptions": {
    "_class": "exportOptions",
    "do_objectID": "CD16D143-2778-4D44-8B6F-54FEF27DBEA5",
    "exportFormats": [
    ],
    "includedLayerIds": [
    ],
    "layerOptions": 0,
    "shouldTrim": false
  },
  "frame": {
    "_class": "rect",
    "constrainProportions": false,
    "do_objectID": "0AE0F547-76F6-40C6-AD4A-B2E3F1A387FE",
    "height": 24,
    "width": 24,
    "x": 2024,
    "y": 757
  },
  "groupLayout": {
    "_class": "MSImmutableFreeformGroupLayout",
    "do_objectID": "74DEE251-BCFA-4D6D-A191-4E23BC983419"
  },
  "hasBackgroundColor": false,
  "hasClickThrough": true,
  "hasClippingMask": false,
  "horizontalRulerData": {
    "_class": "rulerData",
    "base": 0,
    "do_objectID": "0D437AC4-293A-4AEC-B67C-C01A3BE307D1",
    "guides": [
    ]
  },
  "includeBackgroundColorInExport": true,
  "includeBackgroundColorInInstance": true,
  "includeInCloudUpload": true,
  "isFixedToViewport": false,
  "isFlippedHorizontal": false,
  "isFlippedVertical": false,
  "isFlowHome": false,
  "isLocked": false,
  "isVisible": true,
  "layerListExpandedType": 0,
  "layers": [
    {
      "class": "shapeGroup",
      "id": "11133FF8-84B8-4ACA-AE88-86DBB4F6227B"
    },
    {
      "class": "symbolInstance",
      "id": "5A40F5D8-A52D-4874-9B1C-B93A8376343C"
    }
  ],
  "name": "icon/social/location_city_24px",
  "nameIsFixed": false,
  "overrideProperties": [
    {
      "_class": "MSImmutableOverrideProperty",
      "canOverride": true,
      "overrideName": "5A40F5D8-A52D-4874-9B1C-B93A8376343C_symbolID"
    }
  ],
  "resizesContent": false,
  "resizingConstraint": 63,
  "resizingType": 0,
  "rotation": 0,
  "shouldBreakMaskChain": true,
  "style": {
    "_class": "style",
    "do_objectID": "A7E6D7C2-BE7F-4031-B363-C3BAEF84AC7A",
    "endMarkerType": 0,
    "miterLimit": 10,
    "startMarkerType": 0,
    "windingRule": 1
  },
  "symbolID": "D150EEE9-A3C6-43C9-A41C-9DD1F639AA7F",
  "userInfo": {
    "com.amoreaux.sketch-icons": {
      "color": "E5F72CF9-765C-453C-BB5F-4971859D9CB9",
      "padding": 0
    },
    "com.google.ux.material.spec_tools": {
      "iconStyle": "FILLED",
      "symbolName": "icon/social/location_city_24px",
      "type": "icon"
    }
  },
  "verticalRulerData": {
    "_class": "rulerData",
    "base": 0,
    "do_objectID": "A49113DC-844C-4FF9-9DBB-7FE33D95882A",
    "guides": [
    ]
  }
}