{
  "_class": "symbolInstance",
  "booleanOperation": 0,
  "clippingMaskMode": 0,
  "do_objectID": "B91D984F-751C-438E-BCC8-8F9119632821",
  "exportOptions": {
    "_class": "exportOptions",
    "do_objectID": "7F5DF87D-91BF-479F-A593-613069F757C9",
    "exportFormats": [
    ],
    "includedLayerIds": [
    ],
    "layerOptions": 0,
    "shouldTrim": false
  },
  "frame": {
    "_class": "rect",
    "constrainProportions": false,
    "do_objectID": "481BD7A1-FAEA-48A4-88F3-AAD68FB5927C",
    "height": 24,
    "width": 24,
    "x": 0,
    "y": 0
  },
  "hasClippingMask": false,
  "horizontalSpacing": 0,
  "isFixedToViewport": false,
  "isFlippedHorizontal": false,
  "isFlippedVertical": false,
  "isLocked": false,
  "isVisible": true,
  "layerListExpandedType": 0,
  "name": "↳ Color",
  "nameIsFixed": false,
  "overrideValues": [
  ],
  "resizingConstraint": 63,
  "resizingType": 0,
  "rotation": 0,
  "scale": 1,
  "shouldBreakMaskChain": false,
  "style": {
    "_class": "style",
    "do_objectID": "7FA376E5-6EAE-4B46-B908-402B1CFCCB63",
    "endMarkerType": 0,
    "miterLimit": 10,
    "startMarkerType": 0,
    "windingRule": 1
  },
  "symbolID": "644C9856-4728-41E1-A524-9F2EFF68D7F2",
  "verticalSpacing": 0
}