{
  "_class": "shapeGroup",
  "booleanOperation": 0,
  "clippingMaskMode": 0,
  "do_objectID": "80AD0488-5833-4A44-BCB5-8FE044FDB3B6",
  "exportOptions": {
    "_class": "exportOptions",
    "do_objectID": "83EF6B81-7114-425E-9BEB-FA24CDE2AB80",
    "exportFormats": [
    ],
    "includedLayerIds": [
    ],
    "layerOptions": 0,
    "shouldTrim": false
  },
  "frame": {
    "_class": "rect",
    "constrainProportions": false,
    "do_objectID": "90DA6F22-5062-420B-94E8-060F5AFAADD6",
    "height": 20,
    "width": 10,
    "x": 7,
    "y": 2
  },
  "groupLayout": {
    "_class": "MSImmutableFreeformGroupLayout",
    "do_objectID": "ABC8D859-7490-42A5-B9D0-81BF217F628A"
  },
  "hasClickThrough": false,
  "hasClippingMask": true,
  "isFixedToViewport": false,
  "isFlippedHorizontal": false,
  "isFlippedVertical": false,
  "isLocked": false,
  "isVisible": true,
  "layerListExpandedType": 1,
  "layers": [
    {
      "class": "shapePath",
      "id": "3DC75485-0626-4477-9FEA-F8F422A034DB"
    },
    {
      "class": "shapePath",
      "id": "F110674E-8326-4248-A799-1A46E12CD5EA"
    }
  ],
  "name": "icon/device/thermostat_24px",
  "nameIsFixed": false,
  "resizingConstraint": 63,
  "resizingType": 0,
  "rotation": 0,
  "shouldBreakMaskChain": false,
  "style": {
    "_class": "style",
    "do_objectID": "C65CE437-B033-4520-A809-2883E3643157",
    "endMarkerType": 0,
    "fills": [
      {
        "_class": "fill",
        "color": {
          "_class": "color",
          "alpha": 1,
          "blue": 0,
          "green": 0,
          "red": 0
        },
        "fillType": 0,
        "isEnabled": false,
        "noiseIndex": 0,
        "noiseIntensity": 0,
        "patternFillType": 1,
        "patternTileScale": 1
      }
    ],
    "miterLimit": 10,
    "startMarkerType": 0,
    "windingRule": 0
  },
  "windingRule": 0
}