{
  "_class": "shapeGroup",
  "booleanOperation": 0,
  "clippingMaskMode": 0,
  "do_objectID": "C1C23F2D-7420-4D91-9010-12D2A76B0D0C",
  "exportOptions": {
    "_class": "exportOptions",
    "do_objectID": "0BEEA2DB-0BA0-4291-A62E-6E5E6B960989",
    "exportFormats": [
    ],
    "includedLayerIds": [
    ],
    "layerOptions": 0,
    "shouldTrim": false
  },
  "frame": {
    "_class": "rect",
    "constrainProportions": false,
    "do_objectID": "3D619439-0E76-406C-8D1D-10B5A275E3F3",
    "height": 21,
    "width": 24,
    "x": 0,
    "y": 3
  },
  "groupLayout": {
    "_class": "MSImmutableFreeformGroupLayout",
    "do_objectID": "EFE53D80-C8FD-4247-8A72-6016ED091DEA"
  },
  "hasClickThrough": false,
  "hasClippingMask": true,
  "isFixedToViewport": false,
  "isFlippedHorizontal": false,
  "isFlippedVertical": false,
  "isLocked": false,
  "isVisible": true,
  "layerListExpandedType": 0,
  "layers": [
    {
      "class": "shapePath",
      "id": "01EF08A5-4A42-4048-8ACA-0A24784448EB"
    },
    {
      "class": "shapePath",
      "id": "8C78A3B5-8555-4D25-9967-D18F82B2C17C"
    },
    {
      "class": "shapePath",
      "id": "F0E40178-428C-4992-8DEB-39D72B190515"
    }
  ],
  "name": "icon/editor/format_color_text_24px",
  "nameIsFixed": false,
  "resizingConstraint": 63,
  "resizingType": 0,
  "rotation": 0,
  "shouldBreakMaskChain": false,
  "style": {
    "_class": "style",
    "do_objectID": "8EF0E358-BD7E-48B4-8F18-F04C75BC3639",
    "endMarkerType": 0,
    "fills": [
      {
        "_class": "fill",
        "color": {
          "_class": "color",
          "alpha": 0.36,
          "blue": 0,
          "green": 0,
          "red": 0
        },
        "fillType": 0,
        "isEnabled": false,
        "noiseIndex": 0,
        "noiseIntensity": 0,
        "patternFillType": 1,
        "patternTileScale": 1
      }
    ],
    "miterLimit": 10,
    "startMarkerType": 0,
    "windingRule": 0
  },
  "windingRule": 0
}