{
  "_class": "symbolMaster",
  "backgroundColor": {
    "_class": "color",
    "alpha": 1,
    "blue": 1,
    "do_objectID": "6C7596EA-3671-4CFB-8DA0-1DA4A97F57E7",
    "green": 1,
    "red": 1
  },
  "booleanOperation": 0,
  "changeIdentifier": 339,
  "clippingMaskMode": 0,
  "do_objectID": "980D3E16-9D1A-4E87-A730-AC4D493DA867",
  "exportOptions": {
    "_class": "exportOptions",
    "do_objectID": "79D7A920-266F-46E6-A57F-3A0D29AEFD6D",
    "exportFormats": [
    ],
    "includedLayerIds": [
    ],
    "layerOptions": 0,
    "shouldTrim": false
  },
  "frame": {
    "_class": "rect",
    "constrainProportions": false,
    "do_objectID": "D8301ACB-BBF3-4FBC-8BE6-9C412438E948",
    "height": 24,
    "width": 24,
    "x": -820,
    "y": 661
  },
  "groupLayout": {
    "_class": "MSImmutableFreeformGroupLayout",
    "do_objectID": "A25F973A-62A4-4234-AC07-66C3A55A6A22"
  },
  "hasBackgroundColor": false,
  "hasClickThrough": true,
  "hasClippingMask": false,
  "horizontalRulerData": {
    "_class": "rulerData",
    "base": 0,
    "do_objectID": "87AA2E87-153F-42ED-B0CE-E889B0D98BC5",
    "guides": [
    ]
  },
  "includeBackgroundColorInExport": true,
  "includeBackgroundColorInInstance": true,
  "includeInCloudUpload": true,
  "isFixedToViewport": false,
  "isFlippedHorizontal": false,
  "isFlippedVertical": false,
  "isFlowHome": false,
  "isLocked": false,
  "isVisible": true,
  "layerListExpandedType": 0,
  "layers": [
    {
      "class": "shapeGroup",
      "id": "E60FA5BF-5AAE-486E-B2C0-1F63831EEB15"
    },
    {
      "class": "symbolInstance",
      "id": "C99DE60C-DD8B-4D30-9E72-4CC113533444"
    }
  ],
  "name": "icon/action/settings_input_hdmi_24px",
  "nameIsFixed": false,
  "overrideProperties": [
    {
      "_class": "MSImmutableOverrideProperty",
      "canOverride": true,
      "overrideName": "C99DE60C-DD8B-4D30-9E72-4CC113533444_symbolID"
    }
  ],
  "resizesContent": false,
  "resizingConstraint": 63,
  "resizingType": 0,
  "rotation": 0,
  "shouldBreakMaskChain": true,
  "style": {
    "_class": "style",
    "do_objectID": "4AA88D02-E7DA-44B3-B322-44AF5852EA66",
    "endMarkerType": 0,
    "miterLimit": 10,
    "startMarkerType": 0,
    "windingRule": 1
  },
  "symbolID": "7D0A6061-6368-4D2F-BA50-23BF9F882109",
  "userInfo": {
    "com.amoreaux.sketch-icons": {
      "color": "E5F72CF9-765C-453C-BB5F-4971859D9CB9",
      "padding": 0
    },
    "com.google.ux.material.spec_tools": {
      "iconStyle": "FILLED",
      "symbolName": "icon/action/settings_input_hdmi_24px",
      "type": "icon"
    }
  },
  "verticalRulerData": {
    "_class": "rulerData",
    "base": 0,
    "do_objectID": "95B53EAA-AB77-4DAC-9E11-1502145BBA24",
    "guides": [
    ]
  }
}